[
    {
        "Region": {
            "title": "Twig | Обратная связь",
            "alias": "twig_feedback_send",
            "block_count": 1
        },
        "Block": [
            {
                "title": "Twig | Обратная связь",
                "alias": "twig_feedback_send",
                "body": "{% if feedback.Feedback.alias == 'order_call' %}\r\n    {{ croogo_region alias = \"twig_order_call\" }}\r\n{% endif %}",
                "params": "disabledCkEditor=1"
            }
        ]
    }
]
